actfast/__init__.py
actfast/__init__.pyi
actfast/actfast.cpython-314t-aarch64-linux-musl.so
actfast/py.typed
actfast-1.2.0.dist-info/METADATA
actfast-1.2.0.dist-info/WHEEL
actfast-1.2.0.dist-info/licenses/LICENSE
actfast.libs/libgcc_s-39080030.so.1
actfast-1.2.0.dist-info/RECORD
